okta_client/__init__.py
okta_client/get_okta_group.py
okta_client/get_okta_user.py
okta_client-0.1.5.dist-info/METADATA
okta_client-0.1.5.dist-info/WHEEL
okta_client-0.1.5.dist-info/entry_points.txt
okta_client-0.1.5.dist-info/RECORD
